odoo/addons/l10n_es_genci_purchase/README.rst
odoo/addons/l10n_es_genci_purchase/__init__.py
odoo/addons/l10n_es_genci_purchase/__manifest__.py
odoo/addons/l10n_es_genci_purchase/i18n/ca.po
odoo/addons/l10n_es_genci_purchase/i18n/es.po
odoo/addons/l10n_es_genci_purchase/models/__init__.py
odoo/addons/l10n_es_genci_purchase/models/purchase_order.py
odoo/addons/l10n_es_genci_purchase/models/purchase_order_line.py
odoo/addons/l10n_es_genci_purchase/readme/CONTRIBUTORS.md
odoo/addons/l10n_es_genci_purchase/readme/DESCRIPTION.md
odoo/addons/l10n_es_genci_purchase/readme/INSTALL.md
odoo/addons/l10n_es_genci_purchase/readme/ROADMAP.md
odoo/addons/l10n_es_genci_purchase/readme/USAGE.md
odoo/addons/l10n_es_genci_purchase/report/purchase_report_template.xml
odoo/addons/l10n_es_genci_purchase/static/description/icon.png
odoo/addons/l10n_es_genci_purchase/static/description/index.html
odoo/addons/l10n_es_genci_purchase/tests/__init__.py
odoo/addons/l10n_es_genci_purchase/tests/test_l10n_es_genci_purchase.py
odoo/addons/l10n_es_genci_purchase/views/purchase_order_views.xml
odoo_addon_l10n_es_genci_purchase-16.0.1.1.0.dist-info/METADATA
odoo_addon_l10n_es_genci_purchase-16.0.1.1.0.dist-info/WHEEL
odoo_addon_l10n_es_genci_purchase-16.0.1.1.0.dist-info/top_level.txt
odoo_addon_l10n_es_genci_purchase-16.0.1.1.0.dist-info/RECORD
